CHANGES.txt
README.txt
buildout.cfg
setup.py
src/z3c/__init__.py
src/z3c.davapp.zopefile.egg-info/PKG-INFO
src/z3c.davapp.zopefile.egg-info/SOURCES.txt
src/z3c.davapp.zopefile.egg-info/dependency_links.txt
src/z3c.davapp.zopefile.egg-info/namespace_packages.txt
src/z3c.davapp.zopefile.egg-info/not-zip-safe
src/z3c.davapp.zopefile.egg-info/requires.txt
src/z3c.davapp.zopefile.egg-info/top_level.txt
src/z3c/davapp/__init__.py
src/z3c/davapp/zopefile/__init__.py
src/z3c/davapp/zopefile/configure.zcml
src/z3c/davapp/zopefile/defaultview.txt
src/z3c/davapp/zopefile/defaultview.zcml
src/z3c/davapp/zopefile/ftesting.zcml
src/z3c/davapp/zopefile/properties.txt
src/z3c/davapp/zopefile/properties.zcml
src/z3c/davapp/zopefile/tests.py