Metadata-Version: 1.0
Name: z3c.davapp.zopefile
Version: 1.0b1
Summary: Define the WebDAV data model for the  File and Image objects from the
